{
    "lastUpdate": "2023/03/06",
    "currentYearEvents": [

        {
            "years": 2023,
            "title": "大港開唱",
            "tableImages": null,
            "imageURL": null,
            "startDate": "2023/04/01",
            "endDate": "2023/04/02",
            "location": {"locationName": "高雄駁二藝術特區​", "locationAddress": "高雄市鹽埕區大勇路1號", "latitude": 22.620891421969407, "longitude": 120.28135703863754},
            "mail": "megaportfest@gmail.com",
            "latestAttend": "❝  ウエスP /  Wes-P (JP) ❞",
            "ticketStatus": "soldOut",
            "instagramUrl": {"url": "https://www.instagram.com/megaportfest/", "clickable": true},
            "purchaseUrl":  {"url": "https://sslive.kktix.cc/events/breakingmudfest2022kaohsiung", "clickable": false},
            "description": "自2006年起，至今已經邁入第十三個年頭，大港開唱，是搖滾男女們對高雄音樂場景的集體記憶，橫跨世代、超越性別，我們相約每年在春天的高雄相見，在港邊帶上最年輕的靈魂、搖滾的血液，一同見證我們最熱血的時刻。\n\n大港開唱多次將我們兒時只能在小小的電視銀幕裡看到的大明星們請上舞台，從《黃金夜總會》的賀一航、《古惑仔》裡的大飛哥-黃秋生，到唱著《少年吔，安啦！》的伍佰以及後來變成姐姐的謝金燕，大明星的風采在大港開唱魅力四射，震懾了台下的男男女女，演出樂團更是集結國內外實力堅強的樂團還有南台灣在地口味的樂團們，每每都讓台下的樂迷驚喜連連，更是創造了南方港都風味的獨特回憶。\n\n人生就像音樂祭，不一定能夠看到所有的風景，也曾誤打誤撞被路途中的景色衝擊內心深處，因而留下深刻的印象，趕場的時候有時是一個人、有時是一群人，但真正的朋友總會有默契地在同一個地方遇見，只要一個眼神交會，我們就知道要一起往前衝、大聲吶喊，我們在散場時互相敲杯喝盡手中的啤酒，言語無需太多，此刻已進駐人生。\n\n人生的音樂祭，音樂祭的人生。​",
            "eventLastUpdate": "2023/01/24",
            "eventTicket": null,
            "lineUp": "閃靈 ft. 珂拉琪｜滅火器 Fire EX.｜ALI (JP)｜Balming Tiger (KR)｜STUTS (JP)｜鄭宜農 Enno Cheng｜落日飛車｜蔡秋鳳 ft. 邵大倫｜康士坦的變化球｜大象體操｜生祥樂隊｜Crystal Lake (JP)｜TRASH｜1976｜ウエスP /WES-P (JP)｜ 風籟坊 X 橙草 克拉克｜隨性 Random ft. 柯有倫｜潤少 ft. XL Army｜芒果醬｜理想混蛋｜閃閃閃閃｜昆蟲白｜來吧！焙焙！｜SoulFa 靈魂沙發｜wannasleep｜ The Tic Tac ｜FUTURE AFTER A SECOND｜青虫 aoi｜逃走鮑伯｜Dharma 達摩樂隊｜桃子A1J｜當代電影大師｜Manic Sheep｜黑狼開水滾燙請小心使用那卡西｜陳柏惟＋呱吉｜Limi｜Robot Swing｜So-So Heroes瘦瘦英雄 ｜莉莉周她說｜Cicada｜黃子軒與山平快｜Lacuna 라쿠나 (KR)｜BEYOND CURE｜老破麻 O.S.D.｜Sauljaljui戴曉君｜ 李紅 REDLEE ​ ｜凹與山 Our Shame｜Kivi｜暴行終止 Endtrocity｜Super Napkin｜Bremen Entertainment Inc. 布萊梅 ｜Lilidelacrows｜變裝皇后瑪麗安之大港妖姬戰隊｜河豚子｜夕陽武士｜裝咖人｜SADOG｜粗大Band｜李友廷｜漫才少爺｜迷幻幼稚園｜賴皮 DJ MR. SKIN｜DJ WooHoo｜DJ YU｜DJ AfuroGeorge｜DJ SamuelMie｜劉大維｜琳誼 Ring｜邱舒｜王水源 Lifloo｜無菌室… and more"
        },
        {
            "years": 2023,
            "title": "台灣祭",
            "tableImages": null,
            "imageURL": null,
            "startDate": "2023/04/01",
            "endDate": "2023/04/02",
            "location": null,
            "mail": null,
            "latestAttend": "無妄合作社 No-nonsense Collective| 南西肯恩| 貳伍吸菸所 Smoking Area 25| 海岸乾杯Coastal Kanpai| 男子漢樂團",
            "ticketStatus": "free",
            "instagramUrl": null,
            "purchaseUrl":  null,
            "description": "台灣最南端的祭典，一期一會​",
            "eventLastUpdate": "2023/02/27",
            "eventTicket": null,
            "lineUp": "玖壹壹｜黃明志｜deca joins｜董事長｜1976｜麋先生｜康士坦的變化球｜怕胖團｜Marz 23｜羅百吉｜無妄合作社｜GIGO ｜海豚刑警｜NAP the NAP(THI)｜Head Phone President(JP)｜神棍樂團｜南西肯恩｜OVDS｜先知瑪莉｜胖虎｜P!SCO｜荷爾蒙少年｜溫室雜草｜溫蒂漫步｜冰球樂團｜靈魂沙發｜OBSESS｜老破麻｜固定客｜芒果醬｜打倒三明治｜西屯純愛組｜Multiverse｜逃走鮑伯｜wannasleep｜Gummy B｜潮州土狗｜SHOOT UP｜步行者｜餵飽豬｜貳伍吸菸所｜粗大Band｜鐵擊｜PIZZALI｜庸俗救星｜COLD DEW｜恕樂團｜絕命青年｜五木｜阿法｜DIZLIKE｜眠氣｜海岸乾杯｜男子漢｜胡凱兒｜震樂堂｜PEATLE｜SiNNER MOON｜REX｜卜星慧｜Alien Avenge｜暴君｜暴弒者｜非我｜TommyWhipping｜月宵◇クレシェンテ feat. 陽光◆スペクトラ-BAND SET- ｜等阮返來｜生炒鴨肉羹｜八青哥｜行樂人｜碎紙花｜昼食彼女 Lunch Girls ｜日蝕エクリプス｜Ruka Banana｜時不我予｜廢埕｜VIBER氣氛人｜蘭花刀｜野蠻人｜胭脂虎 ｜Traveller旅人｜YOKKORIO｜ZENBØ｜大成｜0o迌迌o0 ｜ MEØWMEØW(HK)｜Control T｜克里夫｜4FUTURES未來肆｜CANDY☆STAR｜木苺FRUCTOSE｜餿水Swill｜粉內Fi-Né｜薄荷綠工廠｜立秋(HK)｜公館青少年 ｜孤兒收容所｜V.V.V.｜姬Revolt｜Primulav｜TOBE｜王立言樂團｜宝島材料行｜四季春｜伯爵白｜上海ブルドッグ(JP)｜『存在証明』NO FACE NO REaLiTY｜慶記KTV｜DJ Double K｜DJ Roman｜G-TER｜DAPUN大胖｜29 Groove｜M3LWA｜NIco｜Zoc｜薄暮｜玖零｜製燥者｜林同學樂團｜城市被忘錄｜卡尼特｜REBELLiOUS & BRiGHT｜花咲＊Chloris｜TOYPLA研修生 ｜海口人｜火熱巨棒。"
        },
        {
            "years": 2023,
            "title": "屏東三大日音樂節",
            "tableImages": null,
            "imageURL": null,
            "startDate": "2023/04/07",
            "endDate": "2023/04/09",
            "location":  {"locationName": "屏東縣立體育館前草地​", "locationAddress": "屏東縣屏東市勝利路9號", "latitude": 22.678046164465005, "longitude": 120.49377761534107},
            "mail": null,
            "latestAttend": "無妄合作社 No-nonsense Collective| 南西肯恩| 貳伍吸菸所 Smoking Area 25| 海岸乾杯Coastal Kanpai| 男子漢樂團",
            "ticketStatus": "free",
            "instagramUrl": null,
            "purchaseUrl":  null,
            "description": "✨2023屏東三大日音樂節✨\n大家最期待的春天音樂盛事即將到來\n📍4月7、8、9日 晚間7點\n📍屏東縣立體育館前草地\n你、妳、你最期待哪位明星來唱歌給你聽​",
            "eventLastUpdate": "2023/02/27",
            "eventTicket": null,
            "lineUp": null
        },
        {
            "years": 2023,
            "title": "B Festival",
            "tableImages": null,
            "imageURL": null,
            "startDate": "2023/04/29",
            "endDate": "2023/04/30",
            "location": null,
            "mail": null,
            "latestAttend": "無妄合作社 No-nonsense Collective| 南西肯恩| 貳伍吸菸所 Smoking Area 25| 海岸乾杯Coastal Kanpai| 男子漢樂團",
            "ticketStatus": "onSale",
            "instagramUrl": null,
            "purchaseUrl":  null,
            "description": "ALRIGHT！ALRIGHT！ALRIGHT！\n\n今年是兔年，NICE 兔 MEET YOU！我們把賽制稍微做了一點改變，時間也稍微做了一點改變，但是絕對一樣B！\n\n之前的兩天活動現在會濃縮成一天半，音樂更濃，派對更濃，酒精更濃，你濃我濃，雖然企劃還沒有全部確認，但是B的貴族盲目票現在馬上開賣，已經開賣！要撿便宜就等現在！\n\n然後我們就順其自然，就是這樣胡搞一通的音樂祭，歡迎大家來到B的世界盡情玩樂吧！共！勉！之！​",
            "eventLastUpdate": "2023/01/09",
            "eventTicket": null,
            "lineUp": null
        },
        {
            "years": 2023,
            "title": "湖畔音樂季",
            "tableImages": null,
            "imageURL": null,
            "startDate": "2023/05/04",
            "endDate": "2023/05/07",
            "location": {"locationName": "中興大學行政後草、雲平前草​", "locationAddress": "台中市南區興大路145號", "latitude": 24.147743970130264,  "longitude": 120.67094583775689},
            "mail": null,
            "latestAttend": null,
            "ticketStatus": "commingSoon",
            "instagramUrl": null,
            "purchaseUrl":  null,
            "description": "2023湖畔音樂季 Lakeside Fest.—湖．托邦》\n．活動時間：2023年5月04-07日\n．活動地點：中興大學行政後草、雲平前草\n．主辦單位：第八屆湖畔音樂季籌備團隊\n．補助單位：台中市政府新聞局​",
            "eventLastUpdate": "2023/01/12",
            "eventTicket": null,
            "lineUp": null
        },
        {
            "years": 2023,
            "title": "台大音樂節",
            "tableImages": null,
            "imageURL": null,
            "startDate": "2023/05/13",
            "endDate": "2023/05/14",
            "location": {"locationName": "台大舊體育館​", "locationAddress": "台北市大安區羅斯福路四段1號", "latitude": 25.020481818809543, "longitude": 121.53662924602568},
            "mail": null,
            "latestAttend": null,
            "ticketStatus": "commingSoon",
            "instagramUrl": null,
            "purchaseUrl":  null,
            "description": "台大音樂節至今已邁入第九屆，我們由不同大專院校學生組成，期望作為學生樂團推手，並建構出一套完善音樂節系統，讓「台大音樂節」成為具影響力的學生音樂節品牌，同時提升大眾對音樂文化、產業及價值的重視。​",
            "eventLastUpdate": "2023/01/12",
            "eventTicket": null,
            "lineUp": "Who Cares 胡凱兒、hue、公館青少年...即將解密，敬請期待！"
        },
        {
            "years": 2023,
            "title": "墾丁草根音樂會",
            "tableImages": null,
            "imageURL": null,
            "startDate": "2023/07/09",
            "endDate": "2023/07/10",
            "location": null,
            "mail": null,
            "latestAttend": null,
            "ticketStatus": "commingSoon",
            "instagramUrl": null,
            "purchaseUrl":  null,
            "description": "墾丁草根音樂會 Grassroots Music Festival\n一年一度恆春半島在地音樂愛好者,與世界及台灣各地音樂人的同樂會​",
            "eventLastUpdate": "2023/01/12",
            "eventTicket": null,
            "lineUp": null
        },
        {
            "years": 2023,
            "title": "無限自由音樂節",
            "tableImages": null,
            "imageURL": null,
            "startDate": "2023/10/27",
            "endDate": "2023/10/29",
            "location": null,
            "mail": null,
            "latestAttend": null,
            "ticketStatus": "commingSoon",
            "instagramUrl": null,
            "purchaseUrl":  null,
            "description": "Unlimited Freedom FESTIVAL 無限自由音樂節\n創辦於2007年夏末秋至，\n為台中第一個最具有規模的獨立音樂節。\n音樂節口號為「Rock In Taichung 搖滾台中！」\n『Unlimited Freedom FESTIVAL 搖滾台中-無限自由音樂節』為台中獨立廠牌 Roc steady co搖滾開跑音樂社（迴響音樂藝文展演空間前身）於2007年所創辦。​",
            "eventLastUpdate": "2023/01/12",
            "eventTicket": null,
            "lineUp": null
        }
    ],
    "nextYearEvents": []
}
