{
    "totalEvent":
    [
        {
            "years": 2021,
            "name": "大港開唱",
            "period": "2021/03/27 - 2021/03/28",
            "type":"mega",
            "location": {"locationName": "高雄駁二藝術特區", "locationAddress": "高雄市鹽埕區大勇路1號", "latitude": 22.620218, "longitude": 120.281550},
            "status": ""
        },
        {
            "years": 2021,
            "name": "浮現祭",
            "period": "2021/02/27 - 2021/02/28",
            "type":"emergeLive",
            "location": {"locationName": "山海一線－台中清水​", "locationAddress": "台中市清水區中山路90號​", "latitude": 24.265556817801844, "longitude": 120.57407563994859},
            "status": ""
        },
        {
            "years": 2021,
            "name": "爛泥發芽(高雄)",
            "period": "2021/01/30 - 2020/01/31",
            "type":"breakingMudKao",
            "location": {"locationName": "高雄橋頭糖廠十鼓文化園區", "locationAddress": "高雄市橋頭區糖廠路24號", "latitude": 22.755359, "longitude": 120.313787},
            "status": ""
        },
        {
            "years": 2021,
            "name": "台大音樂節",
            "period": "2021/01/30 - 2020/01/31",
            "type":"ntu",
            "location": {"locationName": "臺灣大學舊體育館及舊體育館後草皮", "locationAddress": "台北市大安區羅斯福路四段1號", "latitude": 25.019875665434647, "longitude": 121.53622158194536},
            "status": ""
        },
        {
            "years": 2020,
            "name": "SimpleLife簡單生活節",
            "period": "2020/12/12 - 2020/12/13",
            "type":"simpleLife",
            "location": {"locationName": "華山 1914 文化創意產業園區", "locationAddress": "台北市中正區八德路一段1號", "latitude": 25.043474, "longitude": 121.529283},
            "status": ""
        },
        {
            "years": 2020,
            "name": "搖滾連續祭",
            "period": "2020/12/04 - 2020/12/06",
            "type":"comboRock",
            "location": {"locationName": "歷史建築帝國製糖廠臺中營業所", "locationAddress": "台中市東區泉源里樂業路30號", "latitude": 24.137981, "longitude": 120.692164},
            "status": ""
        },
        {
            "years": 2020,
            "name": "貴人散步音樂節",
            "period": "2020/11/27 - 2020/11/29",
            "type":"lucFest",
            "location": {"locationName": "臺南市美術館2館", "locationAddress": "台南市中西區忠義路二段1號", "latitude": 22.990638, "longitude": 120.201376},
            "status": ""
        }
    ]
}
